{
  "version": 1,
  "beans": {
    "gozer-9bu9": {
      "clickup": {
        "task_id": "868h4jjrf",
        "synced_at": "2026-01-18T16:27:04.523366Z"
      }
    },
    "gozer-9n0f": {
      "clickup": {
        "task_id": "868h4jxx6",
        "synced_at": "2026-01-18T18:42:27.361685Z"
      }
    },
    "gozer-iynv": {
      "clickup": {
        "task_id": "868h4jx7w",
        "synced_at": "2026-01-18T18:31:41.496634Z"
      }
    },
    "gozer-miqk": {
      "clickup": {
        "task_id": "868h4jxeg",
        "synced_at": "2026-01-18T18:35:18.553764Z"
      }
    }
  }
}